entrogrammer/__init__.py
entrogrammer/classifier.py
entrogrammer/core.py
entrogrammer/plot.py
entrogrammer/tools.py
entrogrammer-0.2.0.dist-info/LICENSE
entrogrammer-0.2.0.dist-info/METADATA
entrogrammer-0.2.0.dist-info/WHEEL
entrogrammer-0.2.0.dist-info/top_level.txt
entrogrammer-0.2.0.dist-info/RECORD
