Metadata-Version: 2.1
Name: entrogrammer
Version: 0.2.0
Summary: Entrogram calculator
Home-page: https://github.com/elbeejay/entrogrammer
Author: J. Hariharan
Author-email: jayaram.hariharan@utexas.edu
License: MIT
Platform: UNKNOWN
Classifier: Programming Language :: Python :: 3.7
Classifier: Programming Language :: Python :: 3.8
Requires-Dist: numpy
Requires-Dist: matplotlib
Requires-Dist: scipy
Requires-Dist: xarray
Requires-Dist: numba
